gacha_exp_calc/__init__.py
gacha_exp_calc/gacha_func.py
gacha_exp_calc/gacha_type.py
gacha_exp_calc-1.0.0.dist-info/LICENSE.txt
gacha_exp_calc-1.0.0.dist-info/METADATA
gacha_exp_calc-1.0.0.dist-info/WHEEL
gacha_exp_calc-1.0.0.dist-info/top_level.txt
gacha_exp_calc-1.0.0.dist-info/RECORD
